help_rating/__init__.py
help_rating/apps.py
help_rating/cms_plugins.py
help_rating/constants.py
help_rating/models.py
help_rating/receivers.py
help_rating/urls.py
help_rating/utils.py
help_rating/views.py
help_rating/admin/__init__.py
help_rating/admin/feedback.py
help_rating/admin/summary.py
help_rating/locale/cs/LC_MESSAGES/django.mo
help_rating/locale/cs/LC_MESSAGES/django.po
help_rating/migrations/0001_initial.py
help_rating/migrations/0002_feedbacksummary.py
help_rating/migrations/__init__.py
help_rating/static/help_rating/img/smiley-fill.svg
help_rating/static/help_rating/img/smiley-meh-fill.svg
help_rating/static/help_rating/img/smiley-sad-fill.svg
help_rating/static/help_rating/js/send-answer.js
help_rating/templates/help_rating/rating-plugin.html
help_rating/tests/__init__.py
help_rating/tests/settings.py
help_rating/tests/test_models.py
djangocms_help_rating-1.0.1.dist-info/METADATA
djangocms_help_rating-1.0.1.dist-info/WHEEL
djangocms_help_rating-1.0.1.dist-info/top_level.txt
djangocms_help_rating-1.0.1.dist-info/RECORD
